fornt_py_orm/Types.py
fornt_py_orm/__init__.py
fornt_py_orm/exceptions.py
fornt_py_orm/front_py_orm.py
front_py_orm-0.0.1.dist-info/METADATA
front_py_orm-0.0.1.dist-info/RECORD
front_py_orm-0.0.1.dist-info/WHEEL
front_py_orm-0.0.1.dist-info/top_level.txt
