Metadata-Version: 2.1
Name: front-py-orm
Version: 0.0.1
Summary: ORM for sqlite which allows using objects from database as reactive objects.
Home-page: https://github.com/DimonLuk/front-py-orm
Author: Dima Lukashov
Author-email: lds4ever2000@gmail.com
License: UNKNOWN
Platform: UNKNOWN
Classifier: Programming Language :: Python :: 3
Classifier: License :: OSI Approved :: GNU General Public License v3 (GPLv3)
Classifier: Operating System :: OS Independent
